pyenv_inspect/__init__.py
pyenv_inspect/exceptions.py
pyenv_inspect/inspect.py
pyenv_inspect/path.py
pyenv_inspect/spec.py
pyenv_inspect/version.py
pyenv_inspect-0.5.0.dist-info/licenses/LICENSE
pyenv_inspect-0.5.0.dist-info/METADATA
pyenv_inspect-0.5.0.dist-info/WHEEL
pyenv_inspect-0.5.0.dist-info/top_level.txt
pyenv_inspect-0.5.0.dist-info/zip-safe
pyenv_inspect-0.5.0.dist-info/RECORD
